{
  "label": "post_72",
  "source_url": "https://finance.naver.com/item/board_read.naver?code=048530&nid=414142103&page=33",
  "mobile_url": "https://m.stock.naver.com/pc/domestic/stock/048530/discussion/414142103",
  "title": "머야 아직 시총 2천억이네 1조 가야지",
  "written_at": "2026-03-05T04:58:53",
  "author": "억",
  "recommend_count": 8,
  "view_count": 91,
  "image_urls": [],
  "extracted_links": [],
  "saved_images": [],
  "text_filename": "post_72.content.txt",
  "html_filename": "post_72.content.html"
}