{
  "tdy_pred_cntr": [
    {
      "tm": "150900",
      "cur_prc": "-49150",
      "pred_pre": "-1750",
      "pre_rt": "-3.44",
      "pri_sel_bid_unit": "-49150",
      "pri_buy_bid_unit": "-48900",
      "cntr_trde_qty": "7750",
      "sign": "5",
      "acc_trde_qty": "2207254",
      "acc_trde_prica": "121108",
      "cntr_str": "75.22",
      "stex_tp": "KRX"
    },
    {
      "tm": "150800",
      "cur_prc": "-49050",
      "pred_pre": "-1850",
      "pre_rt": "-3.63",
      "pri_sel_bid_unit": "-49050",
      "pri_buy_bid_unit": "-48900",
      "cntr_trde_qty": "7330",
      "sign": "5",
      "acc_trde_qty": "2199504",
      "acc_trde_prica": "120730",
      "cntr_str": "75.22",
      "stex_tp": "KRX"
    },
    {
      "tm": "150700",
      "cur_prc": "-48950",
      "pred_pre": "-1950",
      "pre_rt": "-3.83",
      "pri_sel_bid_unit": "-49000",
      "pri_buy_bid_unit": "-48950",
      "cntr_trde_qty": "9771",
      "sign": "5",
      "acc_trde_qty": "2192174",
      "acc_trde_prica": "120373",
      "cntr_str": "75.36",
      "stex_tp": "KRX"
    },
    {
      "tm": "150600",
      "cur_prc": "-48500",
      "pred_pre": "-2400",
      "pre_rt": "-4.72",
      "pri_sel_bid_unit": "-48500",
      "pri_buy_bid_unit": "-48450",
      "cntr_trde_qty": "7047",
      "sign": "5",
      "acc_trde_qty": "2182403",
      "acc_trde_prica": "119898",
      "cntr_str": "75.43",
      "stex_tp": "KRX"
    },
    {
      "tm": "150500",
      "cur_prc": "-48200",
      "pred_pre": "-2700",
      "pre_rt": "-5.30",
      "pri_sel_bid_unit": "-48200",
      "pri_buy_bid_unit": "-48150",
      "cntr_trde_qty": "10612",
      "sign": "5",
      "acc_trde_qty": "2175356",
      "acc_trde_prica": "119558",
      "cntr_str": "75.35",
      "stex_tp": "KRX"
    },
    {
      "tm": "150400",
      "cur_prc": "-48300",
      "pred_pre": "-2600",
      "pre_rt": "-5.11",
      "pri_sel_bid_unit": "-48350",
      "pri_buy_bid_unit": "-48200",
      "cntr_trde_qty": "10413",
      "sign": "5",
      "acc_trde_qty": "2164744",
      "acc_trde_prica": "119046",
      "cntr_str": "75.52",
      "stex_tp": "KRX"
    },
    {
      "tm": "150300",
      "cur_prc": "-47350",
      "pred_pre": "-3550",
      "pre_rt": "-6.97",
      "pri_sel_bid_unit": "-47550",
      "pri_buy_bid_unit": "-47350",
      "cntr_trde_qty": "7898",
      "sign": "5",
      "acc_trde_qty": "2154331",
      "acc_trde_prica": "118549",
      "cntr_str": "75.21",
      "stex_tp": "KRX"
    },
    {
      "tm": "150200",
      "cur_prc": "-47700",
      "pred_pre": "-3200",
      "pre_rt": "-6.29",
      "pri_sel_bid_unit": "-47700",
      "pri_buy_bid_unit": "-47500",
      "cntr_trde_qty": "5225",
      "sign": "5",
      "acc_trde_qty": "2146433",
      "acc_trde_prica": "118175",
      "cntr_str": "75.13",
      "stex_tp": "KRX"
    },
    {
      "tm": "150100",
      "cur_prc": "-47750",
      "pred_pre": "-3150",
      "pre_rt": "-6.19",
      "pri_sel_bid_unit": "-47800",
      "pri_buy_bid_unit": "-47750",
      "cntr_trde_qty": "5958",
      "sign": "5",
      "acc_trde_qty": "2141208",
      "acc_trde_prica": "117926",
      "cntr_str": "75.15",
      "stex_tp": "KRX"
    },
    {
      "tm": "150000",
      "cur_prc": "-47800",
      "pred_pre": "-3100",
      "pre_rt": "-6.09",
      "pri_sel_bid_unit": "-47800",
      "pri_buy_bid_unit": "-47550",
      "cntr_trde_qty": "17871",
      "sign": "5",
      "acc_trde_qty": "2135250",
      "acc_trde_prica": "117642",
      "cntr_str": "74.97",
      "stex_tp": "KRX"
    },
    {
      "tm": "145900",
      "cur_prc": "-48200",
      "pred_pre": "-2700",
      "pre_rt": "-5.30",
      "pri_sel_bid_unit": "-48250",
      "pri_buy_bid_unit": "-48050",
      "cntr_trde_qty": "8824",
      "sign": "5",
      "acc_trde_qty": "2117379",
      "acc_trde_prica": "116789",
      "cntr_str": "75.00",
      "stex_tp": "KRX"
    },
    {
      "tm": "145800",
      "cur_prc": "-48400",
      "pred_pre": "-2500",
      "pre_rt": "-4.91",
      "pri_sel_bid_unit": "-48500",
      "pri_buy_bid_unit": "-48400",
      "cntr_trde_qty": "7624",
      "sign": "5",
      "acc_trde_qty": "2108555",
      "acc_trde_prica": "116364",
      "cntr_str": "75.10",
      "stex_tp": "KRX"
    },
    {
      "tm": "145700",
      "cur_prc": "-48550",
      "pred_pre": "-2350",
      "pre_rt": "-4.62",
      "pri_sel_bid_unit": "-48600",
      "pri_buy_bid_unit": "-48500",
      "cntr_trde_qty": "4517",
      "sign": "5",
      "acc_trde_qty": "2100931",
      "acc_trde_prica": "115995",
      "cntr_str": "74.70",
      "stex_tp": "KRX"
    },
    {
      "tm": "145600",
      "cur_prc": "-48750",
      "pred_pre": "-2150",
      "pre_rt": "-4.22",
      "pri_sel_bid_unit": "-48750",
      "pri_buy_bid_unit": "-48650",
      "cntr_trde_qty": "1832",
      "sign": "5",
      "acc_trde_qty": "2096414",
      "acc_trde_prica": "115775",
      "cntr_str": "74.68",
      "stex_tp": "KRX"
    },
    {
      "tm": "145500",
      "cur_prc": "-48800",
      "pred_pre": "-2100",
      "pre_rt": "-4.13",
      "pri_sel_bid_unit": "-48950",
      "pri_buy_bid_unit": "-48800",
      "cntr_trde_qty": "6767",
      "sign": "5",
      "acc_trde_qty": "2094582",
      "acc_trde_prica": "115685",
      "cntr_str": "74.71",
      "stex_tp": "KRX"
    },
    {
      "tm": "145400",
      "cur_prc": "-48750",
      "pred_pre": "-2150",
      "pre_rt": "-4.22",
      "pri_sel_bid_unit": "-48800",
      "pri_buy_bid_unit": "-48750",
      "cntr_trde_qty": "4453",
      "sign": "5",
      "acc_trde_qty": "2087815",
      "acc_trde_prica": "115355",
      "cntr_str": "74.68",
      "stex_tp": "KRX"
    },
    {
      "tm": "145300",
      "cur_prc": "-48850",
      "pred_pre": "-2050",
      "pre_rt": "-4.03",
      "pri_sel_bid_unit": "-48900",
      "pri_buy_bid_unit": "-48850",
      "cntr_trde_qty": "2191",
      "sign": "5",
      "acc_trde_qty": "2083362",
      "acc_trde_prica": "115138",
      "cntr_str": "74.74",
      "stex_tp": "KRX"
    },
    {
      "tm": "145200",
      "cur_prc": "-49250",
      "pred_pre": "-1650",
      "pre_rt": "-3.24",
      "pri_sel_bid_unit": "-49250",
      "pri_buy_bid_unit": "-48950",
      "cntr_trde_qty": "3461",
      "sign": "5",
      "acc_trde_qty": "2081171",
      "acc_trde_prica": "115030",
      "cntr_str": "74.81",
      "stex_tp": "KRX"
    },
    {
      "tm": "145100",
      "cur_prc": "-49200",
      "pred_pre": "-1700",
      "pre_rt": "-3.34",
      "pri_sel_bid_unit": "-49200",
      "pri_buy_bid_unit": "-49100",
      "cntr_trde_qty": "5836",
      "sign": "5",
      "acc_trde_qty": "2077710",
      "acc_trde_prica": "114860",
      "cntr_str": "74.77",
      "stex_tp": "KRX"
    },
    {
      "tm": "145000",
      "cur_prc": "-49350",
      "pred_pre": "-1550",
      "pre_rt": "-3.05",
      "pri_sel_bid_unit": "-49400",
      "pri_buy_bid_unit": "-49350",
      "cntr_trde_qty": "7406",
      "sign": "5",
      "acc_trde_qty": "2071874",
      "acc_trde_prica": "114573",
      "cntr_str": "74.75",
      "stex_tp": "KRX"
    },
    {
      "tm": "144900",
      "cur_prc": "-48800",
      "pred_pre": "-2100",
      "pre_rt": "-4.13",
      "pri_sel_bid_unit": "-48900",
      "pri_buy_bid_unit": "-48750",
      "cntr_trde_qty": "4294",
      "sign": "5",
      "acc_trde_qty": "2064468",
      "acc_trde_prica": "114210",
      "cntr_str": "74.58",
      "stex_tp": "KRX"
    },
    {
      "tm": "144800",
      "cur_prc": "-48850",
      "pred_pre": "-2050",
      "pre_rt": "-4.03",
      "pri_sel_bid_unit": "-48900",
      "pri_buy_bid_unit": "-48850",
      "cntr_trde_qty": "5202",
      "sign": "5",
      "acc_trde_qty": "2060174",
      "acc_trde_prica": "114001",
      "cntr_str": "74.54",
      "stex_tp": "KRX"
    },
    {
      "tm": "144700",
      "cur_prc": "-48950",
      "pred_pre": "-1950",
      "pre_rt": "-3.83",
      "pri_sel_bid_unit": "-48950",
      "pri_buy_bid_unit": "-48900",
      "cntr_trde_qty": "5385",
      "sign": "5",
      "acc_trde_qty": "2054972",
      "acc_trde_prica": "113748",
      "cntr_str": "74.60",
      "stex_tp": "KRX"
    },
    {
      "tm": "144600",
      "cur_prc": "-48650",
      "pred_pre": "-2250",
      "pre_rt": "-4.42",
      "pri_sel_bid_unit": "-48700",
      "pri_buy_bid_unit": "-48650",
      "cntr_trde_qty": "9767",
      "sign": "5",
      "acc_trde_qty": "2049587",
      "acc_trde_prica": "113485",
      "cntr_str": "74.39",
      "stex_tp": "KRX"
    },
    {
      "tm": "144500",
      "cur_prc": "-48700",
      "pred_pre": "-2200",
      "pre_rt": "-4.32",
      "pri_sel_bid_unit": "-48700",
      "pri_buy_bid_unit": "-48650",
      "cntr_trde_qty": "7435",
      "sign": "5",
      "acc_trde_qty": "2039820",
      "acc_trde_prica": "113011",
      "cntr_str": "74.40",
      "stex_tp": "KRX"
    },
    {
      "tm": "144400",
      "cur_prc": "-48750",
      "pred_pre": "-2150",
      "pre_rt": "-4.22",
      "pri_sel_bid_unit": "-48750",
      "pri_buy_bid_unit": "-48700",
      "cntr_trde_qty": "7958",
      "sign": "5",
      "acc_trde_qty": "2032385",
      "acc_trde_prica": "112648",
      "cntr_str": "74.17",
      "stex_tp": "KRX"
    },
    {
      "tm": "144300",
      "cur_prc": "-48850",
      "pred_pre": "-2050",
      "pre_rt": "-4.03",
      "pri_sel_bid_unit": "-48850",
      "pri_buy_bid_unit": "-48800",
      "cntr_trde_qty": "8760",
      "sign": "5",
      "acc_trde_qty": "2024427",
      "acc_trde_prica": "112260",
      "cntr_str": "74.37",
      "stex_tp": "KRX"
    },
    {
      "tm": "144200",
      "cur_prc": "-49100",
      "pred_pre": "-1800",
      "pre_rt": "-3.54",
      "pri_sel_bid_unit": "-49100",
      "pri_buy_bid_unit": "-49000",
      "cntr_trde_qty": "3028",
      "sign": "5",
      "acc_trde_qty": "2015667",
      "acc_trde_prica": "111831",
      "cntr_str": "74.67",
      "stex_tp": "KRX"
    },
    {
      "tm": "144100",
      "cur_prc": "-49100",
      "pred_pre": "-1800",
      "pre_rt": "-3.54",
      "pri_sel_bid_unit": "-49150",
      "pri_buy_bid_unit": "-49100",
      "cntr_trde_qty": "8452",
      "sign": "5",
      "acc_trde_qty": "2012639",
      "acc_trde_prica": "111682",
      "cntr_str": "74.75",
      "stex_tp": "KRX"
    },
    {
      "tm": "144000",
      "cur_prc": "-49350",
      "pred_pre": "-1550",
      "pre_rt": "-3.05",
      "pri_sel_bid_unit": "-49350",
      "pri_buy_bid_unit": "-49300",
      "cntr_trde_qty": "3396",
      "sign": "5",
      "acc_trde_qty": "2004187",
      "acc_trde_prica": "111267",
      "cntr_str": "74.64",
      "stex_tp": "KRX"
    },
    {
      "tm": "143900",
      "cur_prc": "-49450",
      "pred_pre": "-1450",
      "pre_rt": "-2.85",
      "pri_sel_bid_unit": "-49500",
      "pri_buy_bid_unit": "-49450",
      "cntr_trde_qty": "2617",
      "sign": "5",
      "acc_trde_qty": "2000791",
      "acc_trde_prica": "111099",
      "cntr_str": "74.70",
      "stex_tp": "KRX"
    },
    {
      "tm": "143800",
      "cur_prc": "-49400",
      "pred_pre": "-1500",
      "pre_rt": "-2.95",
      "pri_sel_bid_unit": "-49400",
      "pri_buy_bid_unit": "-49350",
      "cntr_trde_qty": "3967",
      "sign": "5",
      "acc_trde_qty": "1998174",
      "acc_trde_prica": "110969",
      "cntr_str": "74.66",
      "stex_tp": "KRX"
    },
    {
      "tm": "143700",
      "cur_prc": "-49600",
      "pred_pre": "-1300",
      "pre_rt": "-2.55",
      "pri_sel_bid_unit": "-49600",
      "pri_buy_bid_unit": "-49550",
      "cntr_trde_qty": "3025",
      "sign": "5",
      "acc_trde_qty": "1994207",
      "acc_trde_prica": "110773",
      "cntr_str": "74.77",
      "stex_tp": "KRX"
    },
    {
      "tm": "143600",
      "cur_prc": "-49300",
      "pred_pre": "-1600",
      "pre_rt": "-3.14",
      "pri_sel_bid_unit": "-49350",
      "pri_buy_bid_unit": "-49300",
      "cntr_trde_qty": "1770",
      "sign": "5",
      "acc_trde_qty": "1991182",
      "acc_trde_prica": "110624",
      "cntr_str": "74.64",
      "stex_tp": "KRX"
    },
    {
      "tm": "143500",
      "cur_prc": "-49400",
      "pred_pre": "-1500",
      "pre_rt": "-2.95",
      "pri_sel_bid_unit": "-49400",
      "pri_buy_bid_unit": "-49350",
      "cntr_trde_qty": "1778",
      "sign": "5",
      "acc_trde_qty": "1989412",
      "acc_trde_prica": "110536",
      "cntr_str": "74.71",
      "stex_tp": "KRX"
    },
    {
      "tm": "143400",
      "cur_prc": "-49600",
      "pred_pre": "-1300",
      "pre_rt": "-2.55",
      "pri_sel_bid_unit": "-49600",
      "pri_buy_bid_unit": "-49550",
      "cntr_trde_qty": "2810",
      "sign": "5",
      "acc_trde_qty": "1987634",
      "acc_trde_prica": "110448",
      "cntr_str": "74.72",
      "stex_tp": "KRX"
    },
    {
      "tm": "143300",
      "cur_prc": "-49550",
      "pred_pre": "-1350",
      "pre_rt": "-2.65",
      "pri_sel_bid_unit": "-49550",
      "pri_buy_bid_unit": "-49500",
      "cntr_trde_qty": "1989",
      "sign": "5",
      "acc_trde_qty": "1984824",
      "acc_trde_prica": "110309",
      "cntr_str": "74.70",
      "stex_tp": "KRX"
    },
    {
      "tm": "143200",
      "cur_prc": "-49650",
      "pred_pre": "-1250",
      "pre_rt": "-2.46",
      "pri_sel_bid_unit": "-49700",
      "pri_buy_bid_unit": "-49650",
      "cntr_trde_qty": "2699",
      "sign": "5",
      "acc_trde_qty": "1982835",
      "acc_trde_prica": "110210",
      "cntr_str": "74.76",
      "stex_tp": "KRX"
    },
    {
      "tm": "143100",
      "cur_prc": "-49400",
      "pred_pre": "-1500",
      "pre_rt": "-2.95",
      "pri_sel_bid_unit": "-49750",
      "pri_buy_bid_unit": "-49400",
      "cntr_trde_qty": "2387",
      "sign": "5",
      "acc_trde_qty": "1980136",
      "acc_trde_prica": "110076",
      "cntr_str": "74.82",
      "stex_tp": "KRX"
    },
    {
      "tm": "143000",
      "cur_prc": "-49600",
      "pred_pre": "-1300",
      "pre_rt": "-2.55",
      "pri_sel_bid_unit": "-49700",
      "pri_buy_bid_unit": "-49600",
      "cntr_trde_qty": "4930",
      "sign": "5",
      "acc_trde_qty": "1977749",
      "acc_trde_prica": "109958",
      "cntr_str": "74.74",
      "stex_tp": "KRX"
    },
    {
      "tm": "142900",
      "cur_prc": "-49700",
      "pred_pre": "-1200",
      "pre_rt": "-2.36",
      "pri_sel_bid_unit": "-49750",
      "pri_buy_bid_unit": "-49650",
      "cntr_trde_qty": "3542",
      "sign": "5",
      "acc_trde_qty": "1972819",
      "acc_trde_prica": "109713",
      "cntr_str": "74.80",
      "stex_tp": "KRX"
    },
    {
      "tm": "142800",
      "cur_prc": "-49750",
      "pred_pre": "-1150",
      "pre_rt": "-2.26",
      "pri_sel_bid_unit": "-49900",
      "pri_buy_bid_unit": "-49750",
      "cntr_trde_qty": "1682",
      "sign": "5",
      "acc_trde_qty": "1969277",
      "acc_trde_prica": "109536",
      "cntr_str": "74.67",
      "stex_tp": "KRX"
    },
    {
      "tm": "142700",
      "cur_prc": "-49800",
      "pred_pre": "-1100",
      "pre_rt": "-2.16",
      "pri_sel_bid_unit": "-49850",
      "pri_buy_bid_unit": "-49800",
      "cntr_trde_qty": "2555",
      "sign": "5",
      "acc_trde_qty": "1967595",
      "acc_trde_prica": "109453",
      "cntr_str": "74.61",
      "stex_tp": "KRX"
    },
    {
      "tm": "142600",
      "cur_prc": "-49850",
      "pred_pre": "-1050",
      "pre_rt": "-2.06",
      "pri_sel_bid_unit": "-49850",
      "pri_buy_bid_unit": "-49800",
      "cntr_trde_qty": "5749",
      "sign": "5",
      "acc_trde_qty": "1965040",
      "acc_trde_prica": "109325",
      "cntr_str": "74.49",
      "stex_tp": "KRX"
    },
    {
      "tm": "142500",
      "cur_prc": "-49450",
      "pred_pre": "-1450",
      "pre_rt": "-2.85",
      "pri_sel_bid_unit": "-49550",
      "pri_buy_bid_unit": "-49450",
      "cntr_trde_qty": "2051",
      "sign": "5",
      "acc_trde_qty": "1959291",
      "acc_trde_prica": "109040",
      "cntr_str": "74.30",
      "stex_tp": "KRX"
    },
    {
      "tm": "142400",
      "cur_prc": "-49650",
      "pred_pre": "-1250",
      "pre_rt": "-2.46",
      "pri_sel_bid_unit": "-49650",
      "pri_buy_bid_unit": "-49400",
      "cntr_trde_qty": "3527",
      "sign": "5",
      "acc_trde_qty": "1957240",
      "acc_trde_prica": "108938",
      "cntr_str": "74.33",
      "stex_tp": "KRX"
    },
    {
      "tm": "142300",
      "cur_prc": "-49400",
      "pred_pre": "-1500",
      "pre_rt": "-2.95",
      "pri_sel_bid_unit": "-49450",
      "pri_buy_bid_unit": "-49300",
      "cntr_trde_qty": "2627",
      "sign": "5",
      "acc_trde_qty": "1953713",
      "acc_trde_prica": "108764",
      "cntr_str": "74.16",
      "stex_tp": "KRX"
    },
    {
      "tm": "142200",
      "cur_prc": "-49300",
      "pred_pre": "-1600",
      "pre_rt": "-3.14",
      "pri_sel_bid_unit": "-49400",
      "pri_buy_bid_unit": "-49300",
      "cntr_trde_qty": "8145",
      "sign": "5",
      "acc_trde_qty": "1951086",
      "acc_trde_prica": "108634",
      "cntr_str": "74.16",
      "stex_tp": "KRX"
    },
    {
      "tm": "142100",
      "cur_prc": "-49350",
      "pred_pre": "-1550",
      "pre_rt": "-3.05",
      "pri_sel_bid_unit": "-49400",
      "pri_buy_bid_unit": "-49300",
      "cntr_trde_qty": "5301",
      "sign": "5",
      "acc_trde_qty": "1942941",
      "acc_trde_prica": "108234",
      "cntr_str": "74.24",
      "stex_tp": "KRX"
    },
    {
      "tm": "142000",
      "cur_prc": "-49200",
      "pred_pre": "-1700",
      "pre_rt": "-3.34",
      "pri_sel_bid_unit": "-49350",
      "pri_buy_bid_unit": "-49200",
      "cntr_trde_qty": "7590",
      "sign": "5",
      "acc_trde_qty": "1937640",
      "acc_trde_prica": "107971",
      "cntr_str": "74.05",
      "stex_tp": "KRX"
    },
    {
      "tm": "141900",
      "cur_prc": "-49550",
      "pred_pre": "-1350",
      "pre_rt": "-2.65",
      "pri_sel_bid_unit": "-49550",
      "pri_buy_bid_unit": "-49500",
      "cntr_trde_qty": "2022",
      "sign": "5",
      "acc_trde_qty": "1930050",
      "acc_trde_prica": "107597",
      "cntr_str": "74.29",
      "stex_tp": "KRX"
    },
    {
      "tm": "141800",
      "cur_prc": "-49450",
      "pred_pre": "-1450",
      "pre_rt": "-2.85",
      "pri_sel_bid_unit": "-49500",
      "pri_buy_bid_unit": "-49400",
      "cntr_trde_qty": "2024",
      "sign": "5",
      "acc_trde_qty": "1928028",
      "acc_trde_prica": "107497",
      "cntr_str": "74.22",
      "stex_tp": "KRX"
    },
    {
      "tm": "141700",
      "cur_prc": "-49550",
      "pred_pre": "-1350",
      "pre_rt": "-2.65",
      "pri_sel_bid_unit": "-49600",
      "pri_buy_bid_unit": "-49500",
      "cntr_trde_qty": "1698",
      "sign": "5",
      "acc_trde_qty": "1926004",
      "acc_trde_prica": "107397",
      "cntr_str": "74.32",
      "stex_tp": "KRX"
    },
    {
      "tm": "141600",
      "cur_prc": "-49500",
      "pred_pre": "-1400",
      "pre_rt": "-2.75",
      "pri_sel_bid_unit": "-49500",
      "pri_buy_bid_unit": "-49450",
      "cntr_trde_qty": "6040",
      "sign": "5",
      "acc_trde_qty": "1924306",
      "acc_trde_prica": "107313",
      "cntr_str": "74.28",
      "stex_tp": "KRX"
    },
    {
      "tm": "141500",
      "cur_prc": "-49350",
      "pred_pre": "-1550",
      "pre_rt": "-3.05",
      "pri_sel_bid_unit": "-49400",
      "pri_buy_bid_unit": "-49350",
      "cntr_trde_qty": "7203",
      "sign": "5",
      "acc_trde_qty": "1918266",
      "acc_trde_prica": "107014",
      "cntr_str": "74.04",
      "stex_tp": "KRX"
    },
    {
      "tm": "141400",
      "cur_prc": "-49650",
      "pred_pre": "-1250",
      "pre_rt": "-2.46",
      "pri_sel_bid_unit": "-49700",
      "pri_buy_bid_unit": "-49650",
      "cntr_trde_qty": "5309",
      "sign": "5",
      "acc_trde_qty": "1911063",
      "acc_trde_prica": "106658",
      "cntr_str": "74.37",
      "stex_tp": "KRX"
    },
    {
      "tm": "141300",
      "cur_prc": "-49850",
      "pred_pre": "-1050",
      "pre_rt": "-2.06",
      "pri_sel_bid_unit": "-49850",
      "pri_buy_bid_unit": "-49800",
      "cntr_trde_qty": "2090",
      "sign": "5",
      "acc_trde_qty": "1905754",
      "acc_trde_prica": "106393",
      "cntr_str": "74.51",
      "stex_tp": "KRX"
    },
    {
      "tm": "141200",
      "cur_prc": "-49950",
      "pred_pre": "-950",
      "pre_rt": "-1.87",
      "pri_sel_bid_unit": "-50000",
      "pri_buy_bid_unit": "-49950",
      "cntr_trde_qty": "6220",
      "sign": "5",
      "acc_trde_qty": "1903664",
      "acc_trde_prica": "106289",
      "cntr_str": "74.64",
      "stex_tp": "KRX"
    },
    {
      "tm": "141100",
      "cur_prc": "-49950",
      "pred_pre": "-950",
      "pre_rt": "-1.87",
      "pri_sel_bid_unit": "-50000",
      "pri_buy_bid_unit": "-49950",
      "cntr_trde_qty": "3033",
      "sign": "5",
      "acc_trde_qty": "1897444",
      "acc_trde_prica": "105979",
      "cntr_str": "74.84",
      "stex_tp": "KRX"
    },
    {
      "tm": "141000",
      "cur_prc": "-50100",
      "pred_pre": "-800",
      "pre_rt": "-1.57",
      "pri_sel_bid_unit": "-50100",
      "pri_buy_bid_unit": "-50000",
      "cntr_trde_qty": "2954",
      "sign": "5",
      "acc_trde_qty": "1894411",
      "acc_trde_prica": "105827",
      "cntr_str": "74.87",
      "stex_tp": "KRX"
    },
    {
      "tm": "140900",
      "cur_prc": "-50500",
      "pred_pre": "-400",
      "pre_rt": "-0.79",
      "pri_sel_bid_unit": "-50500",
      "pri_buy_bid_unit": "-50300",
      "cntr_trde_qty": "3801",
      "sign": "5",
      "acc_trde_qty": "1891457",
      "acc_trde_prica": "105678",
      "cntr_str": "74.92",
      "stex_tp": "KRX"
    },
    {
      "tm": "140800",
      "cur_prc": "-50200",
      "pred_pre": "-700",
      "pre_rt": "-1.38",
      "pri_sel_bid_unit": "-50200",
      "pri_buy_bid_unit": "-50100",
      "cntr_trde_qty": "2835",
      "sign": "5",
      "acc_trde_qty": "1887656",
      "acc_trde_prica": "105487",
      "cntr_str": "74.82",
      "stex_tp": "KRX"
    },
    {
      "tm": "140700",
      "cur_prc": "-49950",
      "pred_pre": "-950",
      "pre_rt": "-1.87",
      "pri_sel_bid_unit": "-50000",
      "pri_buy_bid_unit": "-49950",
      "cntr_trde_qty": "2323",
      "sign": "5",
      "acc_trde_qty": "1884821",
      "acc_trde_prica": "105345",
      "cntr_str": "74.72",
      "stex_tp": "KRX"
    },
    {
      "tm": "140600",
      "cur_prc": "-49950",
      "pred_pre": "-950",
      "pre_rt": "-1.87",
      "pri_sel_bid_unit": "-50000",
      "pri_buy_bid_unit": "-49950",
      "cntr_trde_qty": "1718",
      "sign": "5",
      "acc_trde_qty": "1882498",
      "acc_trde_prica": "105229",
      "cntr_str": "74.72",
      "stex_tp": "KRX"
    },
    {
      "tm": "140500",
      "cur_prc": "-50000",
      "pred_pre": "-900",
      "pre_rt": "-1.77",
      "pri_sel_bid_unit": "-50100",
      "pri_buy_bid_unit": "-50000",
      "cntr_trde_qty": "2463",
      "sign": "5",
      "acc_trde_qty": "1880780",
      "acc_trde_prica": "105143",
      "cntr_str": "74.74",
      "stex_tp": "KRX"
    },
    {
      "tm": "140400",
      "cur_prc": "-50000",
      "pred_pre": "-900",
      "pre_rt": "-1.77",
      "pri_sel_bid_unit": "-50100",
      "pri_buy_bid_unit": "-50000",
      "cntr_trde_qty": "3355",
      "sign": "5",
      "acc_trde_qty": "1878317",
      "acc_trde_prica": "105020",
      "cntr_str": "74.81",
      "stex_tp": "KRX"
    },
    {
      "tm": "140300",
      "cur_prc": "-49850",
      "pred_pre": "-1050",
      "pre_rt": "-2.06",
      "pri_sel_bid_unit": "-49900",
      "pri_buy_bid_unit": "-49850",
      "cntr_trde_qty": "3766",
      "sign": "5",
      "acc_trde_qty": "1874962",
      "acc_trde_prica": "104852",
      "cntr_str": "74.68",
      "stex_tp": "KRX"
    },
    {
      "tm": "140200",
      "cur_prc": "-49750",
      "pred_pre": "-1150",
      "pre_rt": "-2.26",
      "pri_sel_bid_unit": "-49800",
      "pri_buy_bid_unit": "-49750",
      "cntr_trde_qty": "2443",
      "sign": "5",
      "acc_trde_qty": "1871196",
      "acc_trde_prica": "104665",
      "cntr_str": "74.78",
      "stex_tp": "KRX"
    },
    {
      "tm": "140100",
      "cur_prc": "-49700",
      "pred_pre": "-1200",
      "pre_rt": "-2.36",
      "pri_sel_bid_unit": "-49700",
      "pri_buy_bid_unit": "-49650",
      "cntr_trde_qty": "3391",
      "sign": "5",
      "acc_trde_qty": "1868753",
      "acc_trde_prica": "104544",
      "cntr_str": "74.79",
      "stex_tp": "KRX"
    },
    {
      "tm": "140000",
      "cur_prc": "-49800",
      "pred_pre": "-1100",
      "pre_rt": "-2.16",
      "pri_sel_bid_unit": "-49850",
      "pri_buy_bid_unit": "-49800",
      "cntr_trde_qty": "1518",
      "sign": "5",
      "acc_trde_qty": "1865362",
      "acc_trde_prica": "104375",
      "cntr_str": "74.95",
      "stex_tp": "KRX"
    },
    {
      "tm": "135900",
      "cur_prc": "-49800",
      "pred_pre": "-1100",
      "pre_rt": "-2.16",
      "pri_sel_bid_unit": "-49850",
      "pri_buy_bid_unit": "-49750",
      "cntr_trde_qty": "2545",
      "sign": "5",
      "acc_trde_qty": "1863844",
      "acc_trde_prica": "104299",
      "cntr_str": "74.95",
      "stex_tp": "KRX"
    },
    {
      "tm": "135800",
      "cur_prc": "-49950",
      "pred_pre": "-950",
      "pre_rt": "-1.87",
      "pri_sel_bid_unit": "-50000",
      "pri_buy_bid_unit": "-49900",
      "cntr_trde_qty": "2744",
      "sign": "5",
      "acc_trde_qty": "1861299",
      "acc_trde_prica": "104173",
      "cntr_str": "75.00",
      "stex_tp": "KRX"
    },
    {
      "tm": "135700",
      "cur_prc": "-50100",
      "pred_pre": "-800",
      "pre_rt": "-1.57",
      "pri_sel_bid_unit": "-50100",
      "pri_buy_bid_unit": "-50000",
      "cntr_trde_qty": "3131",
      "sign": "5",
      "acc_trde_qty": "1858555",
      "acc_trde_prica": "104036",
      "cntr_str": "75.09",
      "stex_tp": "KRX"
    },
    {
      "tm": "135600",
      "cur_prc": "-49800",
      "pred_pre": "-1100",
      "pre_rt": "-2.16",
      "pri_sel_bid_unit": "-49800",
      "pri_buy_bid_unit": "-49750",
      "cntr_trde_qty": "3325",
      "sign": "5",
      "acc_trde_qty": "1855424",
      "acc_trde_prica": "103879",
      "cntr_str": "75.01",
      "stex_tp": "KRX"
    },
    {
      "tm": "135500",
      "cur_prc": "-49950",
      "pred_pre": "-950",
      "pre_rt": "-1.87",
      "pri_sel_bid_unit": "-50000",
      "pri_buy_bid_unit": "-49950",
      "cntr_trde_qty": "3521",
      "sign": "5",
      "acc_trde_qty": "1852099",
      "acc_trde_prica": "103714",
      "cntr_str": "75.18",
      "stex_tp": "KRX"
    },
    {
      "tm": "135400",
      "cur_prc": "-49950",
      "pred_pre": "-950",
      "pre_rt": "-1.87",
      "pri_sel_bid_unit": "-49950",
      "pri_buy_bid_unit": "-49900",
      "cntr_trde_qty": "1115",
      "sign": "5",
      "acc_trde_qty": "1848578",
      "acc_trde_prica": "103538",
      "cntr_str": "75.17",
      "stex_tp": "KRX"
    },
    {
      "tm": "135300",
      "cur_prc": "-50000",
      "pred_pre": "-900",
      "pre_rt": "-1.77",
      "pri_sel_bid_unit": "-50100",
      "pri_buy_bid_unit": "-49950",
      "cntr_trde_qty": "2533",
      "sign": "5",
      "acc_trde_qty": "1847463",
      "acc_trde_prica": "103482",
      "cntr_str": "75.18",
      "stex_tp": "KRX"
    },
    {
      "tm": "135200",
      "cur_prc": "-50000",
      "pred_pre": "-900",
      "pre_rt": "-1.77",
      "pri_sel_bid_unit": "-50100",
      "pri_buy_bid_unit": "-49950",
      "cntr_trde_qty": "3916",
      "sign": "5",
      "acc_trde_qty": "1844930",
      "acc_trde_prica": "103355",
      "cntr_str": "75.20",
      "stex_tp": "KRX"
    },
    {
      "tm": "135100",
      "cur_prc": "-49850",
      "pred_pre": "-1050",
      "pre_rt": "-2.06",
      "pri_sel_bid_unit": "-49850",
      "pri_buy_bid_unit": "-49800",
      "cntr_trde_qty": "4675",
      "sign": "5",
      "acc_trde_qty": "1841014",
      "acc_trde_prica": "103159",
      "cntr_str": "74.98",
      "stex_tp": "KRX"
    },
    {
      "tm": "135000",
      "cur_prc": "-50000",
      "pred_pre": "-900",
      "pre_rt": "-1.77",
      "pri_sel_bid_unit": "-50100",
      "pri_buy_bid_unit": "-50000",
      "cntr_trde_qty": "3031",
      "sign": "5",
      "acc_trde_qty": "1836339",
      "acc_trde_prica": "102926",
      "cntr_str": "75.05",
      "stex_tp": "KRX"
    },
    {
      "tm": "134900",
      "cur_prc": "-50000",
      "pred_pre": "-900",
      "pre_rt": "-1.77",
      "pri_sel_bid_unit": "-50000",
      "pri_buy_bid_unit": "-49950",
      "cntr_trde_qty": "3111",
      "sign": "5",
      "acc_trde_qty": "1833308",
      "acc_trde_prica": "102775",
      "cntr_str": "75.06",
      "stex_tp": "KRX"
    },
    {
      "tm": "134800",
      "cur_prc": "-50300",
      "pred_pre": "-600",
      "pre_rt": "-1.18",
      "pri_sel_bid_unit": "-50300",
      "pri_buy_bid_unit": "-50200",
      "cntr_trde_qty": "2908",
      "sign": "5",
      "acc_trde_qty": "1830197",
      "acc_trde_prica": "102619",
      "cntr_str": "75.05",
      "stex_tp": "KRX"
    },
    {
      "tm": "134700",
      "cur_prc": "-50200",
      "pred_pre": "-700",
      "pre_rt": "-1.38",
      "pri_sel_bid_unit": "-50200",
      "pri_buy_bid_unit": "-50100",
      "cntr_trde_qty": "9659",
      "sign": "5",
      "acc_trde_qty": "1827289",
      "acc_trde_prica": "102473",
      "cntr_str": "74.97",
      "stex_tp": "KRX"
    },
    {
      "tm": "134500",
      "cur_prc": "-49700",
      "pred_pre": "-1200",
      "pre_rt": "-2.36",
      "pri_sel_bid_unit": "-49750",
      "pri_buy_bid_unit": "-49700",
      "cntr_trde_qty": "9934",
      "sign": "5",
      "acc_trde_qty": "1817630",
      "acc_trde_prica": "101990",
      "cntr_str": "74.83",
      "stex_tp": "KRX"
    },
    {
      "tm": "134400",
      "cur_prc": "-50100",
      "pred_pre": "-800",
      "pre_rt": "-1.57",
      "pri_sel_bid_unit": "-50100",
      "pri_buy_bid_unit": "-50000",
      "cntr_trde_qty": "26149",
      "sign": "5",
      "acc_trde_qty": "1807696",
      "acc_trde_prica": "101495",
      "cntr_str": "74.58",
      "stex_tp": "KRX"
    },
    {
      "tm": "134300",
      "cur_prc": "-50400",
      "pred_pre": "-500",
      "pre_rt": "-0.98",
      "pri_sel_bid_unit": "-50500",
      "pri_buy_bid_unit": "-50400",
      "cntr_trde_qty": "5756",
      "sign": "5",
      "acc_trde_qty": "1781547",
      "acc_trde_prica": "100186",
      "cntr_str": "74.71",
      "stex_tp": "KRX"
    },
    {
      "tm": "134200",
      "cur_prc": "-50500",
      "pred_pre": "-400",
      "pre_rt": "-0.79",
      "pri_sel_bid_unit": "-50600",
      "pri_buy_bid_unit": "-50500",
      "cntr_trde_qty": "2127",
      "sign": "5",
      "acc_trde_qty": "1775791",
      "acc_trde_prica": "99896",
      "cntr_str": "74.88",
      "stex_tp": "KRX"
    },
    {
      "tm": "134100",
      "cur_prc": "-50600",
      "pred_pre": "-300",
      "pre_rt": "-0.59",
      "pri_sel_bid_unit": "-50600",
      "pri_buy_bid_unit": "-50500",
      "cntr_trde_qty": "4824",
      "sign": "5",
      "acc_trde_qty": "1773664",
      "acc_trde_prica": "99789",
      "cntr_str": "74.96",
      "stex_tp": "KRX"
    },
    {
      "tm": "134000",
      "cur_prc": "-50600",
      "pred_pre": "-300",
      "pre_rt": "-0.59",
      "pri_sel_bid_unit": "-50700",
      "pri_buy_bid_unit": "-50600",
      "cntr_trde_qty": "1533",
      "sign": "5",
      "acc_trde_qty": "1768840",
      "acc_trde_prica": "99544",
      "cntr_str": "75.11",
      "stex_tp": "KRX"
    },
    {
      "tm": "133900",
      "cur_prc": "-50700",
      "pred_pre": "-200",
      "pre_rt": "-0.39",
      "pri_sel_bid_unit": "-50800",
      "pri_buy_bid_unit": "-50700",
      "cntr_trde_qty": "2188",
      "sign": "5",
      "acc_trde_qty": "1767307",
      "acc_trde_prica": "99467",
      "cntr_str": "75.17",
      "stex_tp": "KRX"
    },
    {
      "tm": "133800",
      "cur_prc": "-50800",
      "pred_pre": "-100",
      "pre_rt": "-0.20",
      "pri_sel_bid_unit": "50900",
      "pri_buy_bid_unit": "-50800",
      "cntr_trde_qty": "2024",
      "sign": "5",
      "acc_trde_qty": "1765119",
      "acc_trde_prica": "99356",
      "cntr_str": "75.24",
      "stex_tp": "KRX"
    },
    {
      "tm": "133700",
      "cur_prc": "50900",
      "pred_pre": "0",
      "pre_rt": "0.00",
      "pri_sel_bid_unit": "+51000",
      "pri_buy_bid_unit": "50900",
      "cntr_trde_qty": "1472",
      "sign": "3",
      "acc_trde_qty": "1763095",
      "acc_trde_prica": "99253",
      "cntr_str": "75.21",
      "stex_tp": "KRX"
    },
    {
      "tm": "133600",
      "cur_prc": "+51100",
      "pred_pre": "+200",
      "pre_rt": "+0.39",
      "pri_sel_bid_unit": "+51200",
      "pri_buy_bid_unit": "+51100",
      "cntr_trde_qty": "3807",
      "sign": "2",
      "acc_trde_qty": "1761623",
      "acc_trde_prica": "99178",
      "cntr_str": "75.23",
      "stex_tp": "KRX"
    },
    {
      "tm": "133500",
      "cur_prc": "+51300",
      "pred_pre": "+400",
      "pre_rt": "+0.79",
      "pri_sel_bid_unit": "+51300",
      "pri_buy_bid_unit": "+51200",
      "cntr_trde_qty": "2681",
      "sign": "2",
      "acc_trde_qty": "1757816",
      "acc_trde_prica": "98982",
      "cntr_str": "75.29",
      "stex_tp": "KRX"
    },
    {
      "tm": "133400",
      "cur_prc": "+51200",
      "pred_pre": "+300",
      "pre_rt": "+0.59",
      "pri_sel_bid_unit": "+51200",
      "pri_buy_bid_unit": "+51100",
      "cntr_trde_qty": "1893",
      "sign": "2",
      "acc_trde_qty": "1755135",
      "acc_trde_prica": "98845",
      "cntr_str": "75.37",
      "stex_tp": "KRX"
    },
    {
      "tm": "133300",
      "cur_prc": "+51200",
      "pred_pre": "+300",
      "pre_rt": "+0.59",
      "pri_sel_bid_unit": "+51200",
      "pri_buy_bid_unit": "50900",
      "cntr_trde_qty": "1687",
      "sign": "2",
      "acc_trde_qty": "1753242",
      "acc_trde_prica": "98748",
      "cntr_str": "75.31",
      "stex_tp": "KRX"
    },
    {
      "tm": "133200",
      "cur_prc": "-50800",
      "pred_pre": "-100",
      "pre_rt": "-0.20",
      "pri_sel_bid_unit": "50900",
      "pri_buy_bid_unit": "-50700",
      "cntr_trde_qty": "1577",
      "sign": "5",
      "acc_trde_qty": "1751555",
      "acc_trde_prica": "98662",
      "cntr_str": "75.21",
      "stex_tp": "KRX"
    },
    {
      "tm": "133100",
      "cur_prc": "-50800",
      "pred_pre": "-100",
      "pre_rt": "-0.20",
      "pri_sel_bid_unit": "-50800",
      "pri_buy_bid_unit": "-50700",
      "cntr_trde_qty": "1599",
      "sign": "5",
      "acc_trde_qty": "1749978",
      "acc_trde_prica": "98582",
      "cntr_str": "75.17",
      "stex_tp": "KRX"
    },
    {
      "tm": "133000",
      "cur_prc": "50900",
      "pred_pre": "0",
      "pre_rt": "0.00",
      "pri_sel_bid_unit": "50900",
      "pri_buy_bid_unit": "-50800",
      "cntr_trde_qty": "1136",
      "sign": "3",
      "acc_trde_qty": "1748379",
      "acc_trde_prica": "98500",
      "cntr_str": "75.09",
      "stex_tp": "KRX"
    },
    {
      "tm": "132900",
      "cur_prc": "50900",
      "pred_pre": "0",
      "pre_rt": "0.00",
      "pri_sel_bid_unit": "+51100",
      "pri_buy_bid_unit": "50900",
      "cntr_trde_qty": "3592",
      "sign": "3",
      "acc_trde_qty": "1747243",
      "acc_trde_prica": "98443",
      "cntr_str": "75.13",
      "stex_tp": "KRX"
    }
  ],
  "return_code": 0,
  "return_msg": "정상적으로 처리되었습니다",
  "api-id": "ka10084",
  "cont-yn": "Y",
  "next-key": "A115180120002880600643206",
  "resp-cnt": "100",
  "user-data": ""
}